lexoid/api.py
lexoid/core/conversion_utils.py
lexoid/core/llm_selector.py
lexoid/core/model_data/doc_embeddings.npy
lexoid/core/model_data/doc_image_embeddings.npy
lexoid/core/model_data/doc_names.npy
lexoid/core/model_data/image_scaler.pkl
lexoid/core/model_data/scaler.pkl
lexoid/core/parse_type/llm_parser.py
lexoid/core/parse_type/static_parser.py
lexoid/core/prompt_templates.py
lexoid/core/utils.py
lexoid-0.1.19.dist-info/LICENSE
lexoid-0.1.19.dist-info/METADATA
lexoid-0.1.19.dist-info/WHEEL
lexoid-0.1.19.dist-info/RECORD
