Metadata-Version: 2.1
Name: lexoid
Version: 0.1.19
Summary: 
Requires-Python: >=3.10,<4.0
Classifier: Programming Language :: Python :: 3
Classifier: Programming Language :: Python :: 3.10
Classifier: Programming Language :: Python :: 3.11
Classifier: Programming Language :: Python :: 3.12
Classifier: Programming Language :: Python :: 3.13
Requires-Dist: accelerate (>=1.10.1,<2.0.0)
Requires-Dist: anthropic (>=0.60.0,<0.61.0)
Requires-Dist: bs4 (>=0.0.2,<0.0.3)
Requires-Dist: docx2pdf (>=0.1.8,<0.2.0)
Requires-Dist: google-genai (>=1.56.0,<2.0.0)
Requires-Dist: google-generativeai (>=0.8.1,<0.9.0)
Requires-Dist: huggingface-hub (>=0.31.2,<0.32.0)
Requires-Dist: levenshtein (>=0.27.1,<0.28.0)
Requires-Dist: loguru (>=0.7.2,<0.8.0)
Requires-Dist: markdown (>=3.7,<4.0)
Requires-Dist: markdownify (>=0.14.1,<0.15.0)
Requires-Dist: matplotlib (>=3.10.6,<4.0.0)
Requires-Dist: mistralai (>=1.8.2,<2.0.0)
Requires-Dist: nest-asyncio (>=1.6.0,<2.0.0)
Requires-Dist: openai (>=1.47.0,<2.0.0)
Requires-Dist: opencv-python (>=4.10.0.84,<5.0.0.0)
Requires-Dist: openpyxl (>=3.1.5,<4.0.0)
Requires-Dist: paddleocr (>=3.2.0,<4.0.0)
Requires-Dist: paddlepaddle (>=3.2.0,<4.0.0)
Requires-Dist: pandas (>=2.2.3,<3.0.0)
Requires-Dist: pdfplumber (>=0.11.4,<0.12.0)
Requires-Dist: pikepdf (>=9.3.0,<10.0.0)
Requires-Dist: playwright (>=1.49.0,<2.0.0)
Requires-Dist: pptx2md (>=2.0.6,<3.0.0)
Requires-Dist: pypdfium2 (>=4.30.0,<5.0.0)
Requires-Dist: pyqt5 (>=5.15.11,<6.0.0) ; platform_system != "debian"
Requires-Dist: pyqtwebengine (>=5.15.7,<6.0.0) ; platform_system != "debian"
Requires-Dist: python-docx (>=1.1.2,<2.0.0)
Requires-Dist: python-dotenv (>=1.0.0,<2.0.0)
Requires-Dist: scikit-image (>=0.25.2,<0.26.0)
Requires-Dist: scikit-learn (>=1.7.1,<2.0.0)
Requires-Dist: tabulate (>=0.9.0,<0.10.0)
Requires-Dist: together (>=1.5.34,<2.0.0)
Requires-Dist: torch (>=2.7.0,<3.0.0)
Requires-Dist: transformers (>=4.51.3,<5.0.0)
